octanegg/__init__.py
octanegg/api.py
octanegg-1.0.1.dist-info/LICENSE
octanegg-1.0.1.dist-info/METADATA
octanegg-1.0.1.dist-info/WHEEL
octanegg-1.0.1.dist-info/top_level.txt
octanegg-1.0.1.dist-info/RECORD
